anncolvar/__init__.py
anncolvar-0.4.data/scripts/anncolvar
anncolvar-0.4.dist-info/DESCRIPTION.rst
anncolvar-0.4.dist-info/METADATA
anncolvar-0.4.dist-info/RECORD
anncolvar-0.4.dist-info/WHEEL
anncolvar-0.4.dist-info/metadata.json
anncolvar-0.4.dist-info/top_level.txt
