Metadata-Version: 2.0
Name: anncolvar
Version: 0.4
Summary: Coding collective variables by artificial neural networks
Home-page: https://github.com/spiwokv/anncolvar
Author: Vojtech Spiwok, 
Author-email: spiwokv@vscht.cz
License: MIT
Keywords: artificial neural networks molecular dynamics simulation
Platform: UNKNOWN
Classifier: Development Status :: 2 - Pre-Alpha
Classifier: License :: OSI Approved :: MIT License
Classifier: Programming Language :: Python
Classifier: Topic :: Scientific/Engineering :: Artificial Intelligence
Classifier: Topic :: Scientific/Engineering :: Chemistry
Requires-Dist: argparse
Requires-Dist: codecov
Requires-Dist: cython
Requires-Dist: datetime
Requires-Dist: keras
Requires-Dist: mdtraj
Requires-Dist: numpy
